setup.py
bike_module/__init__.py
bike_module/bike_module.py
bike_module.egg-info/PKG-INFO
bike_module.egg-info/SOURCES.txt
bike_module.egg-info/dependency_links.txt
bike_module.egg-info/not-zip-safe
bike_module.egg-info/top_level.txt