Metadata-Version: 2.1
Name: bike-module
Version: 0.1
Summary: Includes differnt functions related to bike data management and customer needs
Author: Hari
